{
    "2024-05-22 14:21:12": {
        "summary": {
            "RECOMMENDATION": "NEUTRAL",
            "BUY": 10,
            "SELL": 7,
            "NEUTRAL": 9
        },
        "indicators": {
            "Recommend.Other": -0.2727272727272727,
            "Recommend.All": 0.06363636363636366,
            "Recommend.MA": 0.4,
            "RSI": 56.38082601807994,
            "RSI[1]": 60.38786510501748,
            "Stoch.K": 53.773584905658716,
            "Stoch.D": 62.61188928792163,
            "Stoch.K[1]": 66.73357420045342,
            "Stoch.D[1]": 70.35984197766511,
            "CCI20": 106.10910038238798,
            "CCI20[1]": 118.41531786752455,
            "ADX": 27.772640226018197,
            "ADX+DI": 19.315854821415712,
            "ADX-DI": 12.010522556630253,
            "ADX+DI[1]": 20.2756681037766,
            "ADX-DI[1]": 12.607330680553805,
            "AO": 0.2224661764706184,
            "AO[1]": 0.23978970588240145,
            "Mom": 0.12999999999999545,
            "Mom[1]": 0.20000000000000284,
            "MACD.macd": 0.11833246436476941,
            "MACD.signal": 0.1249798868992894,
            "Rec.Stoch.RSI": 0,
            "Stoch.RSI.K": 10.880938837632755,
            "Rec.WR": 0,
            "W.R": -53.7735849056623,
            "Rec.BBPower": 0,
            "BBPower": 0.14536896162346125,
            "Rec.UO": 0,
            "UO": 61.504393683190095,
            "close": 94.945,
            "EMA5": 94.98270355071197,
            "SMA5": 95.001,
            "EMA10": 94.95287062979324,
            "SMA10": 94.95600000000009,
            "EMA20": 94.87081167088529,
            "SMA20": 94.87861499999991,
            "EMA30": 94.78677512543383,
            "SMA30": 94.80707666666667,
            "EMA50": 94.65893183763603,
            "SMA50": 94.58164200000006,
            "EMA100": 94.51477234290545,
            "SMA100": 94.39625399999984,
            "EMA200": 94.2741202636546,
            "SMA200": 94.49797999999998,
            "Rec.Ichimoku": 0,
            "Ichimoku.BLine": 94.8575,
            "Rec.VWMA": -1,
            "VWMA": 94.98231612122888,
            "Rec.HullMA9": -1,
            "HullMA9": 95.03618518518518,
            "Pivot.M.Classic.S3": 93.34000000000002,
            "Pivot.M.Classic.S2": 94.14000000000001,
            "Pivot.M.Classic.S1": 94.65000000000002,
            "Pivot.M.Classic.Middle": 94.94000000000001,
            "Pivot.M.Classic.R1": 95.45000000000002,
            "Pivot.M.Classic.R2": 95.74000000000001,
            "Pivot.M.Classic.R3": 96.54,
            "Pivot.M.Fibonacci.S3": 94.14000000000001,
            "Pivot.M.Fibonacci.S2": 94.44560000000001,
            "Pivot.M.Fibonacci.S1": 94.63440000000001,
            "Pivot.M.Fibonacci.Middle": 94.94000000000001,
            "Pivot.M.Fibonacci.R1": 95.24560000000001,
            "Pivot.M.Fibonacci.R2": 95.43440000000001,
            "Pivot.M.Fibonacci.R3": 95.74000000000001,
            "Pivot.M.Camarilla.S3": 94.94,
            "Pivot.M.Camarilla.S2": 95.01333333333334,
            "Pivot.M.Camarilla.S1": 95.08666666666666,
            "Pivot.M.Camarilla.Middle": 94.94000000000001,
            "Pivot.M.Camarilla.R1": 95.23333333333333,
            "Pivot.M.Camarilla.R2": 95.30666666666666,
            "Pivot.M.Camarilla.R3": 95.38,
            "Pivot.M.Woodie.S3": 93.67000000000002,
            "Pivot.M.Woodie.S2": 94.05000000000001,
            "Pivot.M.Woodie.S1": 94.47000000000001,
            "Pivot.M.Woodie.Middle": 94.85000000000001,
            "Pivot.M.Woodie.R1": 95.27000000000001,
            "Pivot.M.Woodie.R2": 95.65,
            "Pivot.M.Woodie.R3": 96.07000000000001,
            "Pivot.M.Demark.S1": 94.79499999999997,
            "Pivot.M.Demark.Middle": 95.01249999999999,
            "Pivot.M.Demark.R1": 95.59499999999997,
            "open": 95,
            "P.SAR": 95.21940000000001,
            "BB.lower": 94.67053668501951,
            "BB.upper": 95.08669331498031,
            "AO[2]": 0.25487794117653095,
            "volume": 27285,
            "change": -0.07893075142075652,
            "low": 94.945,
            "high": 95.06
        },
        "oscillators": {
            "RECOMMENDATION": "SELL",
            "BUY": 0,
            "SELL": 3,
            "NEUTRAL": 8,
            "COMPUTE": {
                "RSI": "NEUTRAL",
                "STOCH.K": "NEUTRAL",
                "CCI": "SELL",
                "ADX": "NEUTRAL",
                "AO": "NEUTRAL",
                "Mom": "SELL",
                "MACD": "SELL",
                "Stoch.RSI": "NEUTRAL",
                "W%R": "NEUTRAL",
                "BBP": "NEUTRAL",
                "UO": "NEUTRAL"
            }
        },
        "moving_averages": {
            "RECOMMENDATION": "BUY",
            "BUY": 10,
            "SELL": 4,
            "NEUTRAL": 1,
            "COMPUTE": {
                "EMA10": "SELL",
                "SMA10": "SELL",
                "EMA20": "BUY",
                "SMA20": "BUY",
                "EMA30": "BUY",
                "SMA30": "BUY",
                "EMA50": "BUY",
                "SMA50": "BUY",
                "EMA100": "BUY",
                "SMA100": "BUY",
                "EMA200": "BUY",
                "SMA200": "BUY",
                "Ichimoku": "NEUTRAL",
                "VWMA": "SELL",
                "HullMA": "SELL"
            }
        }
    },
    "2024-05-22 14:37:04": {
        "summary": {
            "RECOMMENDATION": "NEUTRAL",
            "BUY": 8,
            "SELL": 9,
            "NEUTRAL": 9
        },
        "indicators": {
            "Recommend.Other": -0.09090909090909091,
            "Recommend.All": -0.045454545454545456,
            "Recommend.MA": 0,
            "RSI": 49.97031398520309,
            "RSI[1]": 49.97031398520309,
            "Stoch.K": 33.706033077101544,
            "Stoch.D": 48.531503536185944,
            "Stoch.K[1]": 45.15490333100283,
            "Stoch.D[1]": 59.738995429703,
            "CCI20": -69.20715923378819,
            "CCI20[1]": -12.832896137090827,
            "ADX": 24.503443978169063,
            "ADX+DI": 16.937323877617214,
            "ADX-DI": 16.306728860496715,
            "ADX+DI[1]": 17.480929310308664,
            "ADX-DI[1]": 16.83009527080117,
            "AO": 0.1547897058824077,
            "AO[1]": 0.20071617647063533,
            "Mom": -0.10999999999999943,
            "Mom[1]": -0.015000000000000568,
            "MACD.macd": 0.0896505129383911,
            "MACD.signal": 0.11606329985639804,
            "Rec.Stoch.RSI": 0,
            "Stoch.RSI.K": 7.045326400487588,
            "Rec.WR": 0,
            "W.R": -79.62962962962997,
            "Rec.BBPower": 1,
            "BBPower": -0.20703068595541652,
            "Rec.UO": 0,
            "UO": 57.828691633499105,
            "close": 94.8,
            "EMA5": 94.8895801449191,
            "SMA5": 94.954,
            "EMA10": 94.90350572189695,
            "SMA10": 94.9305000000001,
            "EMA20": 94.8515733711638,
            "SMA20": 94.87186499999991,
            "EMA30": 94.77887704241937,
            "SMA30": 94.81557666666666,
            "EMA50": 94.65900063908207,
            "SMA50": 94.58989600000004,
            "EMA100": 94.51760598536531,
            "SMA100": 94.39610399999985,
            "EMA200": 94.27792446785772,
            "SMA200": 94.49795499999999,
            "Rec.Ichimoku": 0,
            "Ichimoku.BLine": 94.8575,
            "Rec.VWMA": -1,
            "VWMA": 94.97918038576987,
            "Rec.HullMA9": -1,
            "HullMA9": 94.88281481481481,
            "Pivot.M.Classic.S3": 93.34000000000002,
            "Pivot.M.Classic.S2": 94.14000000000001,
            "Pivot.M.Classic.S1": 94.65000000000002,
            "Pivot.M.Classic.Middle": 94.94000000000001,
            "Pivot.M.Classic.R1": 95.45000000000002,
            "Pivot.M.Classic.R2": 95.74000000000001,
            "Pivot.M.Classic.R3": 96.54,
            "Pivot.M.Fibonacci.S3": 94.14000000000001,
            "Pivot.M.Fibonacci.S2": 94.44560000000001,
            "Pivot.M.Fibonacci.S1": 94.63440000000001,
            "Pivot.M.Fibonacci.Middle": 94.94000000000001,
            "Pivot.M.Fibonacci.R1": 95.24560000000001,
            "Pivot.M.Fibonacci.R2": 95.43440000000001,
            "Pivot.M.Fibonacci.R3": 95.74000000000001,
            "Pivot.M.Camarilla.S3": 94.94,
            "Pivot.M.Camarilla.S2": 95.01333333333334,
            "Pivot.M.Camarilla.S1": 95.08666666666666,
            "Pivot.M.Camarilla.Middle": 94.94000000000001,
            "Pivot.M.Camarilla.R1": 95.23333333333333,
            "Pivot.M.Camarilla.R2": 95.30666666666666,
            "Pivot.M.Camarilla.R3": 95.38,
            "Pivot.M.Woodie.S3": 93.67000000000002,
            "Pivot.M.Woodie.S2": 94.05000000000001,
            "Pivot.M.Woodie.S1": 94.47000000000001,
            "Pivot.M.Woodie.Middle": 94.85000000000001,
            "Pivot.M.Woodie.R1": 95.27000000000001,
            "Pivot.M.Woodie.R2": 95.65,
            "Pivot.M.Woodie.R3": 96.07000000000001,
            "Pivot.M.Demark.S1": 94.79499999999997,
            "Pivot.M.Demark.Middle": 95.01249999999999,
            "Pivot.M.Demark.R1": 95.59499999999997,
            "open": 94.79,
            "P.SAR": 95.19822400000001,
            "BB.lower": 94.66417642264133,
            "BB.upper": 95.0795535773585,
            "AO[2]": 0.23978970588240145,
            "volume": 11763,
            "change": 0,
            "low": 94.75,
            "high": 94.83
        },
        "oscillators": {
            "RECOMMENDATION": "NEUTRAL",
            "BUY": 1,
            "SELL": 2,
            "NEUTRAL": 8,
            "COMPUTE": {
                "RSI": "NEUTRAL",
                "STOCH.K": "NEUTRAL",
                "CCI": "NEUTRAL",
                "ADX": "NEUTRAL",
                "AO": "NEUTRAL",
                "Mom": "SELL",
                "MACD": "SELL",
                "Stoch.RSI": "NEUTRAL",
                "W%R": "NEUTRAL",
                "BBP": "BUY",
                "UO": "NEUTRAL"
            }
        },
        "moving_averages": {
            "RECOMMENDATION": "NEUTRAL",
            "BUY": 7,
            "SELL": 7,
            "NEUTRAL": 1,
            "COMPUTE": {
                "EMA10": "SELL",
                "SMA10": "SELL",
                "EMA20": "SELL",
                "SMA20": "SELL",
                "EMA30": "BUY",
                "SMA30": "SELL",
                "EMA50": "BUY",
                "SMA50": "BUY",
                "EMA100": "BUY",
                "SMA100": "BUY",
                "EMA200": "BUY",
                "SMA200": "BUY",
                "Ichimoku": "NEUTRAL",
                "VWMA": "SELL",
                "HullMA": "SELL"
            }
        }
    },
    "2024-05-22 14:52:28": {
        "summary": {
            "RECOMMENDATION": "SELL",
            "BUY": 6,
            "SELL": 11,
            "NEUTRAL": 9
        },
        "indicators": {
            "Recommend.Other": 0.09090909090909091,
            "Recommend.All": -0.15454545454545454,
            "Recommend.MA": -0.4,
            "RSI": 41.70717229617264,
            "RSI[1]": 43.697233870947635,
            "Stoch.K": 7.770515613652532,
            "Stoch.D": 26.61377618832232,
            "Stoch.K[1]": 26.915909620311535,
            "Stoch.D[1]": 46.26812905058927,
            "CCI20": -232.95830479221206,
            "CCI20[1]": -152.8812622672878,
            "ADX": 23.871432356115083,
            "ADX+DI": 15.680751258401436,
            "ADX-DI": 20.356647475645037,
            "ADX+DI[1]": 16.182482536098497,
            "ADX-DI[1]": 17.808328178716433,
            "AO": 0.0455985294118193,
            "AO[1]": 0.14455441176475858,
            "Mom": -0.23000000000000398,
            "Mom[1]": -0.28000000000000114,
            "MACD.macd": 0.04640171884096844,
            "MACD.signal": 0.0999611830835122,
            "Rec.Stoch.RSI": 0,
            "Stoch.RSI.K": 8.289665250534503e-15,
            "Rec.WR": 1,
            "W.R": -97.05882352941238,
            "Rec.BBPower": 0,
            "BBPower": -0.47296507775770635,
            "Rec.UO": 0,
            "UO": 52.45378706333238,
            "close": 94.57,
            "EMA5": 94.74527565216827,
            "SMA5": 94.80199999999999,
            "EMA10": 94.81757906171734,
            "SMA10": 94.89050000000009,
            "EMA20": 94.81010833354729,
            "SMA20": 94.8548649999999,
            "EMA30": 94.75514095851717,
            "SMA30": 94.80807666666666,
            "EMA50": 94.64910518918343,
            "SMA50": 94.59239600000005,
            "EMA100": 94.5153438141033,
            "SMA100": 94.39355399999985,
            "EMA200": 94.27915598103614,
            "SMA200": 94.49658,
            "Rec.Ichimoku": 0,
            "Ichimoku.BLine": 94.88,
            "Rec.VWMA": -1,
            "VWMA": 94.97497243357921,
            "Rec.HullMA9": -1,
            "HullMA9": 94.65233333333333,
            "Pivot.M.Classic.S3": 93.34000000000002,
            "Pivot.M.Classic.S2": 94.14000000000001,
            "Pivot.M.Classic.S1": 94.65000000000002,
            "Pivot.M.Classic.Middle": 94.94000000000001,
            "Pivot.M.Classic.R1": 95.45000000000002,
            "Pivot.M.Classic.R2": 95.74000000000001,
            "Pivot.M.Classic.R3": 96.54,
            "Pivot.M.Fibonacci.S3": 94.14000000000001,
            "Pivot.M.Fibonacci.S2": 94.44560000000001,
            "Pivot.M.Fibonacci.S1": 94.63440000000001,
            "Pivot.M.Fibonacci.Middle": 94.94000000000001,
            "Pivot.M.Fibonacci.R1": 95.24560000000001,
            "Pivot.M.Fibonacci.R2": 95.43440000000001,
            "Pivot.M.Fibonacci.R3": 95.74000000000001,
            "Pivot.M.Camarilla.S3": 94.94,
            "Pivot.M.Camarilla.S2": 95.01333333333334,
            "Pivot.M.Camarilla.S1": 95.08666666666666,
            "Pivot.M.Camarilla.Middle": 94.94000000000001,
            "Pivot.M.Camarilla.R1": 95.23333333333333,
            "Pivot.M.Camarilla.R2": 95.30666666666666,
            "Pivot.M.Camarilla.R3": 95.38,
            "Pivot.M.Woodie.S3": 93.67000000000002,
            "Pivot.M.Woodie.S2": 94.05000000000001,
            "Pivot.M.Woodie.S1": 94.47000000000001,
            "Pivot.M.Woodie.Middle": 94.85000000000001,
            "Pivot.M.Woodie.R1": 95.27000000000001,
            "Pivot.M.Woodie.R2": 95.65,
            "Pivot.M.Woodie.R3": 96.07000000000001,
            "Pivot.M.Demark.S1": 94.79499999999997,
            "Pivot.M.Demark.Middle": 95.01249999999999,
            "Pivot.M.Demark.R1": 95.59499999999997,
            "open": 94.63,
            "P.SAR": 95.16413056,
            "BB.lower": 94.59526495152086,
            "BB.upper": 95.11446504847895,
            "AO[2]": 0.20071617647063533,
            "volume": 13154,
            "change": -0.06340483990278166,
            "low": 94.55,
            "high": 94.63
        },
        "oscillators": {
            "RECOMMENDATION": "NEUTRAL",
            "BUY": 2,
            "SELL": 1,
            "NEUTRAL": 8,
            "COMPUTE": {
                "RSI": "NEUTRAL",
                "STOCH.K": "NEUTRAL",
                "CCI": "NEUTRAL",
                "ADX": "NEUTRAL",
                "AO": "NEUTRAL",
                "Mom": "BUY",
                "MACD": "SELL",
                "Stoch.RSI": "NEUTRAL",
                "W%R": "BUY",
                "BBP": "NEUTRAL",
                "UO": "NEUTRAL"
            }
        },
        "moving_averages": {
            "RECOMMENDATION": "SELL",
            "BUY": 4,
            "SELL": 10,
            "NEUTRAL": 1,
            "COMPUTE": {
                "EMA10": "SELL",
                "SMA10": "SELL",
                "EMA20": "SELL",
                "SMA20": "SELL",
                "EMA30": "SELL",
                "SMA30": "SELL",
                "EMA50": "SELL",
                "SMA50": "SELL",
                "EMA100": "BUY",
                "SMA100": "BUY",
                "EMA200": "BUY",
                "SMA200": "BUY",
                "Ichimoku": "NEUTRAL",
                "VWMA": "SELL",
                "HullMA": "SELL"
            }
        }
    },
    "2024-05-22 15:07:46": {
        "summary": {
            "RECOMMENDATION": "NEUTRAL",
            "BUY": 10,
            "SELL": 9,
            "NEUTRAL": 7
        },
        "indicators": {
            "Recommend.Other": 0.09090909090909091,
            "Recommend.All": 0.045454545454545456,
            "Recommend.MA": 0,
            "RSI": 47.1732808757394,
            "RSI[1]": 42.35007536816072,
            "Stoch.K": 12.499999999999837,
            "Stoch.D": 16.636578926935012,
            "Stoch.K[1]": 10.493827160493623,
            "Stoch.D[1]": 27.521546703936014,
            "CCI20": -144.9010028140934,
            "CCI20[1]": -237.5665677732329,
            "ADX": 22.83108666686165,
            "ADX+DI": 18.16956218270283,
            "ADX-DI": 20.47830380558152,
            "ADX+DI[1]": 15.441374495967828,
            "ADX-DI[1]": 21.572454522289192,
            "AO": -0.013866176470529012,
            "AO[1]": 0.04218676470593152,
            "Mom": -0.18999999999999773,
            "Mom[1]": -0.20999999999999375,
            "MACD.macd": 0.03421563379697545,
            "MACD.signal": 0.08706734388147772,
            "Rec.Stoch.RSI": 0,
            "Stoch.RSI.K": 5.991366126558199,
            "Rec.WR": 0,
            "W.R": -73.61111111111138,
            "Rec.BBPower": 1,
            "BBPower": -0.30172516869029664,
            "Rec.UO": 0,
            "UO": 57.16470751974333,
            "close": 94.7,
            "EMA5": 94.73462821255663,
            "SMA5": 94.748,
            "EMA10": 94.79917625710758,
            "SMA10": 94.87350000000009,
            "EMA20": 94.80134518159949,
            "SMA20": 94.85261499999991,
            "EMA30": 94.75279055328505,
            "SMA30": 94.81107666666666,
            "EMA50": 94.65185462044191,
            "SMA50": 94.60099600000005,
            "EMA100": 94.51938856947544,
            "SMA100": 94.39455399999984,
            "EMA200": 94.28354050853851,
            "SMA200": 94.49688349999998,
            "Rec.Ichimoku": 0,
            "Ichimoku.BLine": 94.87,
            "Rec.VWMA": -1,
            "VWMA": 94.97159698430873,
            "Rec.HullMA9": 1,
            "HullMA9": 94.56618518518515,
            "Pivot.M.Classic.S3": 93.34000000000002,
            "Pivot.M.Classic.S2": 94.14000000000001,
            "Pivot.M.Classic.S1": 94.65000000000002,
            "Pivot.M.Classic.Middle": 94.94000000000001,
            "Pivot.M.Classic.R1": 95.45000000000002,
            "Pivot.M.Classic.R2": 95.74000000000001,
            "Pivot.M.Classic.R3": 96.54,
            "Pivot.M.Fibonacci.S3": 94.14000000000001,
            "Pivot.M.Fibonacci.S2": 94.44560000000001,
            "Pivot.M.Fibonacci.S1": 94.63440000000001,
            "Pivot.M.Fibonacci.Middle": 94.94000000000001,
            "Pivot.M.Fibonacci.R1": 95.24560000000001,
            "Pivot.M.Fibonacci.R2": 95.43440000000001,
            "Pivot.M.Fibonacci.R3": 95.74000000000001,
            "Pivot.M.Camarilla.S3": 94.94,
            "Pivot.M.Camarilla.S2": 95.01333333333334,
            "Pivot.M.Camarilla.S1": 95.08666666666666,
            "Pivot.M.Camarilla.Middle": 94.94000000000001,
            "Pivot.M.Camarilla.R1": 95.23333333333333,
            "Pivot.M.Camarilla.R2": 95.30666666666666,
            "Pivot.M.Camarilla.R3": 95.38,
            "Pivot.M.Woodie.S3": 93.67000000000002,
            "Pivot.M.Woodie.S2": 94.05000000000001,
            "Pivot.M.Woodie.S1": 94.47000000000001,
            "Pivot.M.Woodie.Middle": 94.85000000000001,
            "Pivot.M.Woodie.R1": 95.27000000000001,
            "Pivot.M.Woodie.R2": 95.65,
            "Pivot.M.Woodie.R3": 96.07000000000001,
            "Pivot.M.Demark.S1": 94.79499999999997,
            "Pivot.M.Demark.Middle": 95.01249999999999,
            "Pivot.M.Demark.R1": 95.59499999999997,
            "open": 94.6,
            "P.SAR": 95.1118001152,
            "BB.lower": 94.5911680547793,
            "BB.upper": 95.11406194522053,
            "AO[2]": 0.14455441176475858,
            "volume": 16497,
            "change": 0.11629136272333167,
            "low": 94.6,
            "high": 94.72
        },
        "oscillators": {
            "RECOMMENDATION": "NEUTRAL",
            "BUY": 3,
            "SELL": 2,
            "NEUTRAL": 6,
            "COMPUTE": {
                "RSI": "NEUTRAL",
                "STOCH.K": "NEUTRAL",
                "CCI": "BUY",
                "ADX": "NEUTRAL",
                "AO": "SELL",
                "Mom": "BUY",
                "MACD": "SELL",
                "Stoch.RSI": "NEUTRAL",
                "W%R": "NEUTRAL",
                "BBP": "BUY",
                "UO": "NEUTRAL"
            }
        },
        "moving_averages": {
            "RECOMMENDATION": "NEUTRAL",
            "BUY": 7,
            "SELL": 7,
            "NEUTRAL": 1,
            "COMPUTE": {
                "EMA10": "SELL",
                "SMA10": "SELL",
                "EMA20": "SELL",
                "SMA20": "SELL",
                "EMA30": "SELL",
                "SMA30": "SELL",
                "EMA50": "BUY",
                "SMA50": "BUY",
                "EMA100": "BUY",
                "SMA100": "BUY",
                "EMA200": "BUY",
                "SMA200": "BUY",
                "Ichimoku": "NEUTRAL",
                "VWMA": "SELL",
                "HullMA": "BUY"
            }
        }
    },
    "2024-05-22 15:23:10": {
        "summary": {
            "RECOMMENDATION": "NEUTRAL",
            "BUY": 9,
            "SELL": 8,
            "NEUTRAL": 9
        },
        "indicators": {
            "Recommend.Other": -0.09090909090909091,
            "Recommend.All": 0.02121212121212121,
            "Recommend.MA": 0.13333333333333333,
            "RSI": 49.52697282430415,
            "RSI[1]": 51.92655574018782,
            "Stoch.K": 30.32407407407352,
            "Stoch.D": 19.778806584361778,
            "Stoch.K[1]": 18.518518518518153,
            "Stoch.D[1]": 18.64275176644112,
            "CCI20": -57.198459855172395,
            "CCI20[1]": -76.98828288547031,
            "ADX": 21.78887521116867,
            "ADX+DI": 21.63210758649137,
            "ADX-DI": 18.745539317685754,
            "ADX+DI[1]": 22.40775386119185,
            "ADX-DI[1]": 19.417684076622425,
            "AO": -0.04676323529405124,
            "AO[1]": -0.001924999999957322,
            "Mom": -0.21999999999999886,
            "Mom[1]": -0.060000000000002274,
            "MACD.macd": 0.03622015804008072,
            "MACD.signal": 0.07855716597245707,
            "Rec.Stoch.RSI": 0,
            "Stoch.RSI.K": 20.810977319422165,
            "Rec.WR": 0,
            "W.R": -64.58333333333391,
            "Rec.BBPower": 1,
            "BBPower": -0.05045830785698513,
            "Rec.UO": 0,
            "UO": 54.237732262584736,
            "close": 94.765,
            "EMA5": 94.77364103059331,
            "SMA5": 94.72300000000001,
            "EMA10": 94.81230123515412,
            "SMA10": 94.86450000000009,
            "EMA20": 94.80908554979183,
            "SMA20": 94.8578649999999,
            "EMA30": 94.76142425328123,
            "SMA30": 94.82341,
            "EMA50": 94.66118981025926,
            "SMA50": 94.61329600000005,
            "EMA100": 94.52677544419026,
            "SMA100": 94.39800399999986,
            "EMA200": 94.28961181161436,
            "SMA200": 94.49748349999999,
            "Rec.Ichimoku": 0,
            "Ichimoku.BLine": 94.87,
            "Rec.VWMA": -1,
            "VWMA": 94.96552327297108,
            "Rec.HullMA9": 1,
            "HullMA9": 94.63529629629629,
            "Pivot.M.Classic.S3": 93.34000000000002,
            "Pivot.M.Classic.S2": 94.14000000000001,
            "Pivot.M.Classic.S1": 94.65000000000002,
            "Pivot.M.Classic.Middle": 94.94000000000001,
            "Pivot.M.Classic.R1": 95.45000000000002,
            "Pivot.M.Classic.R2": 95.74000000000001,
            "Pivot.M.Classic.R3": 96.54,
            "Pivot.M.Fibonacci.S3": 94.14000000000001,
            "Pivot.M.Fibonacci.S2": 94.44560000000001,
            "Pivot.M.Fibonacci.S1": 94.63440000000001,
            "Pivot.M.Fibonacci.Middle": 94.94000000000001,
            "Pivot.M.Fibonacci.R1": 95.24560000000001,
            "Pivot.M.Fibonacci.R2": 95.43440000000001,
            "Pivot.M.Fibonacci.R3": 95.74000000000001,
            "Pivot.M.Camarilla.S3": 94.94,
            "Pivot.M.Camarilla.S2": 95.01333333333334,
            "Pivot.M.Camarilla.S1": 95.08666666666666,
            "Pivot.M.Camarilla.Middle": 94.94000000000001,
            "Pivot.M.Camarilla.R1": 95.23333333333333,
            "Pivot.M.Camarilla.R2": 95.30666666666666,
            "Pivot.M.Camarilla.R3": 95.38,
            "Pivot.M.Woodie.S3": 93.67000000000002,
            "Pivot.M.Woodie.S2": 94.05000000000001,
            "Pivot.M.Woodie.S1": 94.47000000000001,
            "Pivot.M.Woodie.Middle": 94.85000000000001,
            "Pivot.M.Woodie.R1": 95.27000000000001,
            "Pivot.M.Woodie.R2": 95.65,
            "Pivot.M.Woodie.R3": 96.07000000000001,
            "Pivot.M.Demark.S1": 94.79499999999997,
            "Pivot.M.Demark.Middle": 95.01249999999999,
            "Pivot.M.Demark.R1": 95.59499999999997,
            "open": 94.83,
            "P.SAR": 95.063656105984,
            "BB.lower": 94.60401578259035,
            "BB.upper": 95.11171421740946,
            "AO[2]": 0.04218676470593152,
            "volume": 69886,
            "change": -0.06854370979647552,
            "low": 94.75,
            "high": 94.84
        },
        "oscillators": {
            "RECOMMENDATION": "NEUTRAL",
            "BUY": 1,
            "SELL": 2,
            "NEUTRAL": 8,
            "COMPUTE": {
                "RSI": "NEUTRAL",
                "STOCH.K": "NEUTRAL",
                "CCI": "NEUTRAL",
                "ADX": "NEUTRAL",
                "AO": "NEUTRAL",
                "Mom": "SELL",
                "MACD": "SELL",
                "Stoch.RSI": "NEUTRAL",
                "W%R": "NEUTRAL",
                "BBP": "BUY",
                "UO": "NEUTRAL"
            }
        },
        "moving_averages": {
            "RECOMMENDATION": "BUY",
            "BUY": 8,
            "SELL": 6,
            "NEUTRAL": 1,
            "COMPUTE": {
                "EMA10": "SELL",
                "SMA10": "SELL",
                "EMA20": "SELL",
                "SMA20": "SELL",
                "EMA30": "BUY",
                "SMA30": "SELL",
                "EMA50": "BUY",
                "SMA50": "BUY",
                "EMA100": "BUY",
                "SMA100": "BUY",
                "EMA200": "BUY",
                "SMA200": "BUY",
                "Ichimoku": "NEUTRAL",
                "VWMA": "SELL",
                "HullMA": "BUY"
            }
        }
    },
    "2024-05-22 15:38:33": {
        "summary": {
            "RECOMMENDATION": "NEUTRAL",
            "BUY": 9,
            "SELL": 8,
            "NEUTRAL": 9
        },
        "indicators": {
            "Recommend.Other": -0.09090909090909091,
            "Recommend.All": 0.02121212121212121,
            "Recommend.MA": 0.13333333333333333,
            "RSI": 49.79992406170535,
            "RSI[1]": 53.653842170836846,
            "Stoch.K": 44.44444444444357,
            "Stoch.D": 32.870370370369706,
            "Stoch.K[1]": 35.648148148147364,
            "Stoch.D[1]": 21.553497942386397,
            "CCI20": -34.87222456208464,
            "CCI20[1]": 8.580201151835668,
            "ADX": 21.85556658685388,
            "ADX+DI": 22.903320820812375,
            "ADX-DI": 16.851058129074744,
            "ADX+DI[1]": 24.354197864971024,
            "ADX-DI[1]": 17.918537102998947,
            "AO": -0.057366176470523556,
            "AO[1]": -0.036527941176416334,
            "Mom": -0.18999999999999773,
            "Mom[1]": -0.10500000000000398,
            "MACD.macd": 0.03753243310829646,
            "MACD.signal": 0.07182002566743305,
            "Rec.Stoch.RSI": 0,
            "Stoch.RSI.K": 35.191529052714216,
            "Rec.WR": 0,
            "W.R": -62.50000000000049,
            "Rec.BBPower": 1,
            "BBPower": 0.002872470816441819,
            "Rec.UO": 0,
            "UO": 51.98440697011411,
            "close": 94.78,
            "EMA5": 94.80131624261776,
            "SMA5": 94.742,
            "EMA10": 94.82353572132445,
            "SMA10": 94.85700000000008,
            "EMA20": 94.81622479448285,
            "SMA20": 94.8596149999999,
            "EMA30": 94.76956337533802,
            "SMA30": 94.82924333333334,
            "EMA50": 94.67018198225216,
            "SMA50": 94.62659600000002,
            "EMA100": 94.53402192593455,
            "SMA100": 94.40140399999986,
            "EMA200": 94.29562418882608,
            "SMA200": 94.49820849999998,
            "Rec.Ichimoku": 0,
            "Ichimoku.BLine": 94.87,
            "Rec.VWMA": -1,
            "VWMA": 94.96624063139876,
            "Rec.HullMA9": 1,
            "HullMA9": 94.75314814814813,
            "Pivot.M.Classic.S3": 93.34000000000002,
            "Pivot.M.Classic.S2": 94.14000000000001,
            "Pivot.M.Classic.S1": 94.65000000000002,
            "Pivot.M.Classic.Middle": 94.94000000000001,
            "Pivot.M.Classic.R1": 95.45000000000002,
            "Pivot.M.Classic.R2": 95.74000000000001,
            "Pivot.M.Classic.R3": 96.54,
            "Pivot.M.Fibonacci.S3": 94.14000000000001,
            "Pivot.M.Fibonacci.S2": 94.44560000000001,
            "Pivot.M.Fibonacci.S1": 94.63440000000001,
            "Pivot.M.Fibonacci.Middle": 94.94000000000001,
            "Pivot.M.Fibonacci.R1": 95.24560000000001,
            "Pivot.M.Fibonacci.R2": 95.43440000000001,
            "Pivot.M.Fibonacci.R3": 95.74000000000001,
            "Pivot.M.Camarilla.S3": 94.94,
            "Pivot.M.Camarilla.S2": 95.01333333333334,
            "Pivot.M.Camarilla.S1": 95.08666666666666,
            "Pivot.M.Camarilla.Middle": 94.94000000000001,
            "Pivot.M.Camarilla.R1": 95.23333333333333,
            "Pivot.M.Camarilla.R2": 95.30666666666666,
            "Pivot.M.Camarilla.R3": 95.38,
            "Pivot.M.Woodie.S3": 93.67000000000002,
            "Pivot.M.Woodie.S2": 94.05000000000001,
            "Pivot.M.Woodie.S1": 94.47000000000001,
            "Pivot.M.Woodie.Middle": 94.85000000000001,
            "Pivot.M.Woodie.R1": 95.27000000000001,
            "Pivot.M.Woodie.R2": 95.65,
            "Pivot.M.Woodie.R3": 96.07000000000001,
            "Pivot.M.Demark.S1": 94.79499999999997,
            "Pivot.M.Demark.Middle": 95.01249999999999,
            "Pivot.M.Demark.R1": 95.59499999999997,
            "open": 94.89,
            "P.SAR": 95.01936361750528,
            "BB.lower": 94.60660894241768,
            "BB.upper": 95.11262105758213,
            "AO[2]": -0.001924999999957322,
            "volume": 20789,
            "change": -0.10539629005058423,
            "low": 94.75,
            "high": 94.91
        },
        "oscillators": {
            "RECOMMENDATION": "NEUTRAL",
            "BUY": 1,
            "SELL": 2,
            "NEUTRAL": 8,
            "COMPUTE": {
                "RSI": "NEUTRAL",
                "STOCH.K": "NEUTRAL",
                "CCI": "NEUTRAL",
                "ADX": "NEUTRAL",
                "AO": "NEUTRAL",
                "Mom": "SELL",
                "MACD": "SELL",
                "Stoch.RSI": "NEUTRAL",
                "W%R": "NEUTRAL",
                "BBP": "BUY",
                "UO": "NEUTRAL"
            }
        },
        "moving_averages": {
            "RECOMMENDATION": "BUY",
            "BUY": 8,
            "SELL": 6,
            "NEUTRAL": 1,
            "COMPUTE": {
                "EMA10": "SELL",
                "SMA10": "SELL",
                "EMA20": "SELL",
                "SMA20": "SELL",
                "EMA30": "BUY",
                "SMA30": "SELL",
                "EMA50": "BUY",
                "SMA50": "BUY",
                "EMA100": "BUY",
                "SMA100": "BUY",
                "EMA200": "BUY",
                "SMA200": "BUY",
                "Ichimoku": "NEUTRAL",
                "VWMA": "SELL",
                "HullMA": "BUY"
            }
        }
    }
}